proteome_data_prep/__init__.py
proteome_data_prep/data_container.py
proteome_data_prep/data_loader.py
proteome_data_prep/data_utils.py
proteome_data_prep/process_utils.py
proteome_data_prep/data/acc_by_tf_gene.json
proteome_data_prep/data/bad_batches.txt
proteome_data_prep/data/gene_info_by_acc.json
proteome_data_prep/data/tf_proteins.txt
ProteomeDataPrep-0.3.0.dist-info/METADATA
ProteomeDataPrep-0.3.0.dist-info/WHEEL
ProteomeDataPrep-0.3.0.dist-info/top_level.txt
ProteomeDataPrep-0.3.0.dist-info/RECORD
