Metadata-Version: 2.2
Name: ProteomeDataPrep
Version: 0.3.0
Summary: A package for loading and preprocessing peptide and protein         abundance data from mass spectrometry.
Author: Lillian Tatka
Classifier: Programming Language :: Python :: 3
Classifier: License :: OSI Approved :: MIT License
Classifier: Operating System :: OS Independent
Requires-Python: >=3.6
Requires-Dist: numpy
Requires-Dist: pandas
Requires-Dist: boto3
Requires-Dist: fsspec
Requires-Dist: s3fs
Requires-Dist: dataclasses
Requires-Dist: polars
Requires-Dist: tqdm
Requires-Dist: pyarrow
Dynamic: author
Dynamic: classifier
Dynamic: requires-dist
Dynamic: requires-python
Dynamic: summary
